MANIFEST.in
setup.cfg
setup.py
tenon/__init__.py
tenon/api.py
tenon_python.egg-info/PKG-INFO
tenon_python.egg-info/SOURCES.txt
tenon_python.egg-info/dependency_links.txt
tenon_python.egg-info/requires.txt
tenon_python.egg-info/top_level.txt
tenon_python.egg-info/zip-safe