Metadata-Version: 1.1
Name: tenon-python
Version: 0.1.0
Summary: Python wrapper for the Tenon.io API
Home-page: https://github.com/poorgeek/tenon-python
Author: Justin Stockton
Author-email: poorgeek@gmail.com
License: MIT
Keywords: tenon,tenon.io,accessibility,a11y,testing,api
Platform: UNKNOWN
Classifier: Development Status :: 5 - Production/Stable
Classifier: Environment :: Console
Classifier: Intended Audience :: Developers
Classifier: Natural Language :: English
Classifier: Operating System :: OS Independent
Classifier: Programming Language :: Python
Classifier: Topic :: Software Development :: Libraries :: Python Modules
Classifier: Topic :: Internet :: WWW/HTTP :: Dynamic Content :: CGI Tools/Libraries
Classifier: Topic :: Utilities
Classifier: License :: OSI Approved :: MIT License
